transit_parser/__init__.py
transit_parser/_core.abi3.so
transit_parser/_core.pyi
transit_parser/adapters/__init__.py
transit_parser/dataframes.py
transit_parser/exceptions.py
transit_parser/filtering.py
transit_parser/gtfs/__init__.py
transit_parser/io/__init__.py
transit_parser/py.typed
transit_parser/txc/__init__.py
transit_parser-0.1.0.dist-info/METADATA
transit_parser-0.1.0.dist-info/WHEEL
transit_parser-0.1.0.dist-info/RECORD
