Metadata-Version: 2.4
Name: transit-parser
Version: 0.1.0
Classifier: Development Status :: 4 - Beta
Classifier: Intended Audience :: Developers
Classifier: Programming Language :: Python :: 3
Classifier: Programming Language :: Python :: 3.9
Classifier: Programming Language :: Python :: 3.10
Classifier: Programming Language :: Python :: 3.11
Classifier: Programming Language :: Python :: 3.12
Classifier: Programming Language :: Python :: Implementation :: CPython
Classifier: Programming Language :: Rust
Classifier: Topic :: Scientific/Engineering :: GIS
Classifier: Topic :: Software Development :: Libraries :: Python Modules
Requires-Dist: pytest>=8.0 ; extra == 'dev'
Requires-Dist: pytest-benchmark>=4.0 ; extra == 'dev'
Requires-Dist: mypy>=1.10 ; extra == 'dev'
Requires-Dist: ruff>=0.6 ; extra == 'dev'
Provides-Extra: dev
Summary: High-performance transit data parser with TXC to GTFS conversion
Keywords: gtfs,transxchange,txc,transit,parsing,transport
Author-email: alexogeny <alexogeny@gmail.com>
License: MIT OR Apache-2.0
Requires-Python: >=3.9
Project-URL: Documentation, https://alexogeny.github.io/transit-parser/
Project-URL: Homepage, https://github.com/alexogeny/transit-parser
Project-URL: Issues, https://github.com/alexogeny/transit-parser/issues
Project-URL: Repository, https://github.com/alexogeny/transit-parser
